passagemath_schemes/__init__.py
passagemath_schemes/.dylibs/libgmpxx.4.dylib
passagemath_schemes/.dylibs/libflint.22.0.dylib
passagemath_schemes/.dylibs/libgmp.10.dylib
passagemath_schemes/.dylibs/libmpfr.6.dylib
sage_wheels/share/cremona/cremona_mini.db
sage_wheels/share/ellcurves/rank21
sage_wheels/share/ellcurves/rank19
sage_wheels/share/ellcurves/rank10
sage_wheels/share/ellcurves/rank28
sage_wheels/share/ellcurves/rank17
sage_wheels/share/ellcurves/rank11
sage_wheels/share/ellcurves/rank20
sage_wheels/share/ellcurves/rank2
sage_wheels/share/ellcurves/rank5
sage_wheels/share/ellcurves/rank4
sage_wheels/share/ellcurves/rank3
sage_wheels/share/ellcurves/rank22
sage_wheels/share/ellcurves/rank14
sage_wheels/share/ellcurves/rank12
sage_wheels/share/ellcurves/rank15
sage_wheels/share/ellcurves/rank23
sage_wheels/share/ellcurves/rank24
sage_wheels/share/ellcurves/rank8
sage_wheels/share/ellcurves/rank6
sage_wheels/share/ellcurves/rank1
sage_wheels/share/ellcurves/rank0
sage_wheels/share/ellcurves/rank7
sage_wheels/share/ellcurves/rank9
passagemath_schemes-10.6.43.dist-info/RECORD
passagemath_schemes-10.6.43.dist-info/METADATA.bak
passagemath_schemes-10.6.43.dist-info/WHEEL
passagemath_schemes-10.6.43.dist-info/top_level.txt
passagemath_schemes-10.6.43.dist-info/METADATA
sage/all__sagemath_schemes.py
sage/schemes/all.py
sage/schemes/overview.py
sage/schemes/cyclic_covers/constructor.py
sage/schemes/cyclic_covers/all.py
sage/schemes/cyclic_covers/cycliccover_generic.py
sage/schemes/cyclic_covers/cycliccover_finite_field.py
sage/schemes/cyclic_covers/charpoly_frobenius.py
sage/schemes/berkovich/berkovich_space.py
sage/schemes/berkovich/all.py
sage/schemes/berkovich/berkovich_cp_element.py
sage/schemes/hyperelliptic_curves/jacobian_homset.py
sage/schemes/hyperelliptic_curves/hyperelliptic_padic_field.py
sage/schemes/hyperelliptic_curves/jacobian_morphism.py
sage/schemes/hyperelliptic_curves/constructor.py
sage/schemes/hyperelliptic_curves/hyperelliptic_finite_field.py
sage/schemes/hyperelliptic_curves/jacobian_g2.py
sage/schemes/hyperelliptic_curves/kummer_surface.py
sage/schemes/hyperelliptic_curves/hyperelliptic_rational_field.py
