Metadata-Version: 2.4
Name: passagemath-schemes
Version: 10.6.43
Summary: passagemath: Schemes, varieties, elliptic curves, algebraic Riemann surfaces, modular forms, arithmetic dynamics
Author-email: The Sage Developers <sage-support@googlegroups.com>
Maintainer: Matthias Köppe, passagemath contributors
License-Expression: GPL-2.0-or-later
Project-URL: release notes, https://github.com/passagemath/passagemath/releases
Project-URL: repo (upstream), https://github.com/sagemath/sage
Project-URL: repo, https://github.com/passagemath/passagemath
Project-URL: documentation, https://passagemath.org/docs/latest
Project-URL: homepage (upstream), https://www.sagemath.org
Project-URL: discourse, https://passagemath.discourse.group
Project-URL: tracker (upstream), https://github.com/sagemath/sage/issues
Project-URL: tracker, https://github.com/passagemath/passagemath/issues
Classifier: Development Status :: 6 - Mature
Classifier: Intended Audience :: Education
Classifier: Intended Audience :: Science/Research
Classifier: Operating System :: POSIX
Classifier: Operating System :: POSIX :: Linux
Classifier: Operating System :: MacOS :: MacOS X
Classifier: Programming Language :: Python :: 3 :: Only
Classifier: Programming Language :: Python :: 3.10
Classifier: Programming Language :: Python :: 3.11
Classifier: Programming Language :: Python :: 3.12
Classifier: Programming Language :: Python :: 3.13
Classifier: Programming Language :: Python :: 3.14
Classifier: Programming Language :: Python :: Implementation :: CPython
Classifier: Topic :: Scientific/Engineering :: Mathematics
Requires-Python: <3.15,>=3.10
Requires-Dist: gmpy2~=2.1.b999
Requires-Dist: cysignals!=1.12.4; sys_platform == "win32"
Requires-Dist: cysignals!=1.12.0,>=1.11.2
Requires-Dist: fpylll>=0.5.9
Requires-Dist: memory_allocator
Requires-Dist: scipy>=1.5
Requires-Dist: passagemath-modules~=10.6.43.0
Requires-Dist: passagemath-flint~=10.6.43.0
Requires-Dist: passagemath-polyhedra~=10.6.43.0
Requires-Dist: passagemath-singular~=10.6.43.0
Provides-Extra: test
Requires-Dist: passagemath-repl; extra == "test"
Provides-Extra: flint
Provides-Extra: fpylll
Provides-Extra: gsl
Provides-Extra: linbox
Requires-Dist: passagemath-linbox; extra == "linbox"
Provides-Extra: m4ri
Requires-Dist: passagemath-modules[linbox]; extra == "m4ri"
Provides-Extra: m4rie
Requires-Dist: passagemath-modules[linbox]; extra == "m4rie"
Provides-Extra: meataxe
Requires-Dist: passagemath-meataxe; extra == "meataxe"
Provides-Extra: mpfi
Requires-Dist: passagemath-modules[flint]; extra == "mpfi"
Provides-Extra: mpfr
Provides-Extra: mpmath
Provides-Extra: ntl
Requires-Dist: passagemath-ntl; extra == "ntl"
Provides-Extra: numpy
Requires-Dist: numpy>=1.19; extra == "numpy"
Requires-Dist: numpy>=1.22.4; extra == "numpy"
Provides-Extra: pari
Requires-Dist: passagemath-pari; extra == "pari"
Provides-Extra: primecountpy
Requires-Dist: passagemath-primesieve-primecount; extra == "primecountpy"
Provides-Extra: eclib
Requires-Dist: passagemath-eclib; extra == "eclib"
Provides-Extra: msolve
Requires-Dist: passagemath-msolve; extra == "msolve"
Provides-Extra: palp
Requires-Dist: passagemath-palp; extra == "palp"
Provides-Extra: qepcad
Requires-Dist: passagemath-qepcad; extra == "qepcad"
Provides-Extra: singular
Provides-Extra: sympow
Requires-Dist: passagemath-sympow; extra == "sympow"
Provides-Extra: rdf
Requires-Dist: passagemath-schemes[numpy]; extra == "rdf"
Provides-Extra: cdf
Requires-Dist: passagemath-schemes[numpy]; extra == "cdf"
Provides-Extra: rr
Provides-Extra: cc
Provides-Extra: rif
Provides-Extra: cif
Provides-Extra: rbf
Requires-Dist: passagemath-schemes[flint]; extra == "rbf"
Provides-Extra: cbf
Requires-Dist: passagemath-schemes[flint]; extra == "cbf"
Provides-Extra: gf
Requires-Dist: passagemath-schemes[pari]; extra == "gf"
Provides-Extra: gf2
Requires-Dist: passagemath-schemes[m4ri]; extra == "gf2"
Provides-Extra: gf2e
Requires-Dist: passagemath-schemes[m4rie]; extra == "gf2e"
Provides-Extra: gf2n
Requires-Dist: passagemath-schemes[m4rie]; extra == "gf2n"
Provides-Extra: gfpn
Requires-Dist: passagemath-schemes[meataxe]; extra == "gfpn"
Provides-Extra: qqbar
Requires-Dist: passagemath-schemes[NumberField]; extra == "qqbar"
Provides-Extra: aa
Requires-Dist: passagemath-schemes[NumberField]; extra == "aa"
Provides-Extra: ucf
Requires-Dist: passagemath-schemes[NumberField]; extra == "ucf"
Provides-Extra: zp
Provides-Extra: qp
Requires-Dist: passagemath-schemes[Zp]; extra == "qp"
Provides-Extra: zq
Requires-Dist: passagemath-schemes[Zp]; extra == "zq"
Provides-Extra: qq
Requires-Dist: passagemath-schemes[Zp]; extra == "qq"
Provides-Extra: finitefield
Requires-Dist: passagemath-schemes[GF]; extra == "finitefield"
Provides-Extra: numberfield
Provides-Extra: quadraticfield
Requires-Dist: passagemath-schemes[NumberField]; extra == "quadraticfield"
Provides-Extra: cyclotomicfield
Requires-Dist: passagemath-schemes[NumberField]; extra == "cyclotomicfield"
Provides-Extra: toric
Requires-Dist: passagemath-palp; extra == "toric"
Requires-Dist: passagemath-polyhedra; extra == "toric"
Requires-Dist: passagemath-graphs; extra == "toric"
Provides-Extra: padics
Requires-Dist: passagemath-schemes[Zp]; extra == "padics"
Provides-Extra: database-kohel
Requires-Dist: passagemath-database-kohel; extra == "database-kohel"
Provides-Extra: standard
Requires-Dist: passagemath-schemes[FiniteField,NumberField,eclib,flint,linbox,mpfi,ntl,numpy,padics,pari,singular,sympow,toric]; extra == "standard"
